LICENSE
MANIFEST.in
README.md
setup.py
dragon_rest/__init__.py
dragon_rest/dragons.py
dragon_rest.egg-info/PKG-INFO
dragon_rest.egg-info/SOURCES.txt
dragon_rest.egg-info/dependency_links.txt
dragon_rest.egg-info/requires.txt
dragon_rest.egg-info/top_level.txt
tests/__init__.py
tests/test_dragon_rest.py