Metadata-Version: 2.1
Name: dragon-rest
Version: 0.2.3
Summary: Python wrapper for DragonMint/Innosilicon REST API
Home-page: https://github.com/brndnmtthws/dragon-rest
Author: Brenden Matthews
Author-email: brenden@diddyinc.com
License: UNKNOWN
Platform: UNKNOWN
Classifier: Programming Language :: Python :: 3
Classifier: License :: OSI Approved :: Apache Software License
Classifier: Operating System :: OS Independent
Requires-Python: >=3.6
Provides-Extra: test
